z3smt_mcp/__init__.py
z3smt_mcp/py.typed
z3smt_mcp/server.py
z3smt_mcp/solver.py
z3smt_mcp/translator.py
z3smt_mcp-0.1.0.dist-info/METADATA
z3smt_mcp-0.1.0.dist-info/WHEEL
z3smt_mcp-0.1.0.dist-info/entry_points.txt
z3smt_mcp-0.1.0.dist-info/licenses/LICENSE
z3smt_mcp-0.1.0.dist-info/RECORD
