Metadata-Version: 2.4
Name: z3smt-mcp
Version: 0.1.0
Summary: MCP server for Z3/SMT solver - enables constraint solving and logical reasoning
Project-URL: Homepage, https://github.com/NewJerseyStyle/z3smt-mcp
Project-URL: Repository, https://github.com/NewJerseyStyle/z3smt-mcp
Author: David Xu
License-Expression: MIT
License-File: LICENSE
Keywords: constraint,logic,mcp,smt,solver,z3
Classifier: Development Status :: 4 - Beta
Classifier: Intended Audience :: Developers
Classifier: License :: OSI Approved :: MIT License
Classifier: Programming Language :: Python :: 3
Classifier: Programming Language :: Python :: 3.10
Classifier: Programming Language :: Python :: 3.11
Classifier: Programming Language :: Python :: 3.12
Requires-Python: >=3.10
Requires-Dist: mcp>=1.0.0
Requires-Dist: z3-solver>=4.12.0
Provides-Extra: dev
Requires-Dist: pytest-asyncio>=0.21.0; extra == 'dev'
Requires-Dist: pytest>=7.0.0; extra == 'dev'
